heimdall_py-0.9.11.dist-info/METADATA
heimdall_py-0.9.11.dist-info/WHEEL
heimdall_py/__init__.py
heimdall_py/__init__.pyi
heimdall_py/heimdall_py.abi3.so
heimdall_py/py.typed
heimdall_py-0.9.11.dist-info/RECORD
