Metadata-Version: 2.4
Name: heimdall-py
Version: 0.9.11
Classifier: Programming Language :: Rust
Classifier: Programming Language :: Python :: Implementation :: CPython
Classifier: Programming Language :: Python :: 3.10
Classifier: Programming Language :: Python :: 3.11
Classifier: Programming Language :: Python :: 3.12
Classifier: Development Status :: 4 - Beta
Classifier: Intended Audience :: Developers
Classifier: Topic :: Software Development :: Disassemblers
Classifier: Topic :: Security
Classifier: License :: OSI Approved :: MIT License
Summary: Python bindings for Heimdall - Advanced EVM bytecode analysis toolkit
Keywords: ethereum,evm,decompiler,bytecode,smart-contracts
Home-Page: https://heimdall.rs
License: MIT
Requires-Python: >=3.10
Project-URL: Homepage, https://github.com/jalbrekt85/heimdall-py
Project-URL: Repository, https://github.com/jalbrekt85/heimdall-py
Project-URL: Issues, https://github.com/jalbrekt85/heimdall-py/issues
